flowfoundry/__init__.py
flowfoundry/cli.py
flowfoundry/functional/__init__.py
flowfoundry/functional/chunking/__init__.py
flowfoundry/functional/chunking/fixed.py
flowfoundry/functional/chunking/hybrid.py
flowfoundry/functional/chunking/recursive.py
flowfoundry/functional/composer/__init__.py
flowfoundry/functional/composer/llmcompose.py
flowfoundry/functional/indexing/__init__.py
flowfoundry/functional/indexing/chroma.py
flowfoundry/functional/ingestion/__init__.py
flowfoundry/functional/ingestion/pdf_loader.py
flowfoundry/functional/rerank/__init__.py
flowfoundry/functional/rerank/bm25.py
flowfoundry/functional/rerank/cross_encoder.py
flowfoundry/functional/rerank/identity.py
flowfoundry/model/__init__.py
flowfoundry/model/providers/__init__.py
flowfoundry/model/providers/huggingface_provider.py
flowfoundry/model/providers/langchain_provider.py
flowfoundry/model/providers/ollama_provider.py
flowfoundry/model/providers/openai_provider.py
flowfoundry/plans/__init__.py
flowfoundry/plans/runner.py
flowfoundry/utils/__init__.py
flowfoundry/utils/exceptions.py
flowfoundry/utils/functional_autodiscover.py
flowfoundry/utils/functional_contracts.py
flowfoundry/utils/functional_registry.py
flowfoundry/utils/llm_contracts.py
flowfoundry/utils/llm_registry.py
flowfoundry/utils/plugin_loader.py
flowfoundry/utils/versions.py
flowfoundry-1.2.1.dist-info/licenses/LICENSE
flowfoundry-1.2.1.dist-info/METADATA
flowfoundry-1.2.1.dist-info/WHEEL
flowfoundry-1.2.1.dist-info/entry_points.txt
flowfoundry-1.2.1.dist-info/top_level.txt
flowfoundry-1.2.1.dist-info/RECORD
