Metadata-Version: 2.4
Name: flowfoundry
Version: 1.2.1
Summary: FlowFoundry: a strategy-first, cloud-agnostic agentic workflow framework (LangGraph/LangChain)
Author: Mandar Parab
License: Apache-2.0
Project-URL: Homepage, https://github.com/m-np/flowfoundry
Project-URL: Repository, https://github.com/m-np/flowfoundry
Project-URL: Issues, https://github.com/m-np/flowfoundry/issues
Project-URL: Documentation, https://github.com/m-np/flowfoundry#readme
Keywords: RAG,LangGraph,LangChain,agents,LLM,framework
Classifier: Development Status :: 4 - Beta
Classifier: Intended Audience :: Developers
Classifier: Programming Language :: Python :: 3
Classifier: Programming Language :: Python :: 3 :: Only
Classifier: License :: OSI Approved :: Apache Software License
Classifier: Operating System :: OS Independent
Classifier: Topic :: Scientific/Engineering :: Artificial Intelligence
Requires-Python: >=3.10
License-File: LICENSE
Requires-Dist: pydantic>=2.7
Requires-Dist: pyyaml>=6.0
Requires-Dist: typer>=0.12
Requires-Dist: fastapi>=0.111
Requires-Dist: uvicorn>=0.30
Requires-Dist: langchain>=0.2
Requires-Dist: langchain-community>=0.3
Requires-Dist: langgraph>=0.2
Requires-Dist: pypdf>=4.2
Requires-Dist: langchain-ollama>=0.1.20
Requires-Dist: torch<3,>=2.4
Requires-Dist: torchvision<1,>=0.19
Requires-Dist: transformers>=4.44
Requires-Dist: accelerate>=1.10.1
Requires-Dist: sentence-transformers>=3.0
Requires-Dist: sentencepiece>=0.2.1
Provides-Extra: openai
Requires-Dist: openai>=1.40; extra == "openai"
Requires-Dist: langchain-openai>=0.1.20; extra == "openai"
Provides-Extra: llm-openai
Requires-Dist: langchain-openai>=0.1.20; extra == "llm-openai"
Provides-Extra: rag
Requires-Dist: chromadb>=0.5; extra == "rag"
Requires-Dist: sentence-transformers>=3.0; extra == "rag"
Provides-Extra: search
Requires-Dist: duckduckgo-search>=5.3; extra == "search"
Requires-Dist: tavily-python>=0.3; extra == "search"
Provides-Extra: rerank
Requires-Dist: rank-bm25>=0.2; extra == "rerank"
Requires-Dist: sentence-transformers>=3.0; extra == "rerank"
Provides-Extra: qdrant
Requires-Dist: qdrant-client>=1.9; extra == "qdrant"
Provides-Extra: api
Requires-Dist: fastapi>=0.111; extra == "api"
Requires-Dist: uvicorn>=0.30; extra == "api"
Provides-Extra: dev
Requires-Dist: pytest>=8.2; extra == "dev"
Requires-Dist: pytest-cov>=5.0; extra == "dev"
Requires-Dist: mypy>=1.11; extra == "dev"
Requires-Dist: ruff>=0.5; extra == "dev"
Requires-Dist: black>=24.8; extra == "dev"
Requires-Dist: types-PyYAML>=6.0.12.20240808; extra == "dev"
Requires-Dist: build>=1.2; extra == "dev"
Requires-Dist: twine>=5.1; extra == "dev"
Provides-Extra: local-gpu-cu121
Requires-Dist: torch<3,>=2.4; extra == "local-gpu-cu121"
Requires-Dist: torchvision<1,>=0.19; extra == "local-gpu-cu121"
Requires-Dist: transformers>=4.44; extra == "local-gpu-cu121"
Requires-Dist: accelerate>=1.10; extra == "local-gpu-cu121"
Requires-Dist: sentence-transformers>=3.0; extra == "local-gpu-cu121"
Provides-Extra: local-gpu-cu124
Requires-Dist: torch<3,>=2.4; extra == "local-gpu-cu124"
Requires-Dist: torchvision<1,>=0.19; extra == "local-gpu-cu124"
Requires-Dist: transformers>=4.44; extra == "local-gpu-cu124"
Requires-Dist: accelerate>=1.10; extra == "local-gpu-cu124"
Requires-Dist: sentence-transformers>=3.0; extra == "local-gpu-cu124"
Provides-Extra: local-cpu
Dynamic: license-file
